plonetheme.dsgov-1.0a6-py3.8-nspkg.pth
plonetheme/dsgov/__init__.py
plonetheme/dsgov/configure.zcml
plonetheme/dsgov/interfaces.py
plonetheme/dsgov/permissions.zcml
plonetheme/dsgov/setuphandlers.py
plonetheme/dsgov/testing.py
plonetheme/dsgov/browser/__init__.py
plonetheme/dsgov/browser/configure.zcml
plonetheme/dsgov/browser/controlpanel.py
plonetheme/dsgov/browser/overrides/plone.app.contenttypes.browser.templates.listing.pt
plonetheme/dsgov/browser/overrides/plone.app.contenttypes.browser.templates.newsitem.pt
plonetheme/dsgov/browser/overrides/plone.app.layout.viewlets.globalstatusmessage.pt
plonetheme/dsgov/browser/overrides/plone.app.layout.viewlets.searchbox.pt
plonetheme/dsgov/browser/overrides/plone.app.standardtiles.templates.existingcontent_view.pt
plonetheme/dsgov/browser/templates/tile_album_view.pt
plonetheme/dsgov/browser/templates/tile_cardgrid_view.pt
plonetheme/dsgov/browser/viewlets/__init__.py
plonetheme/dsgov/browser/viewlets/common.py
plonetheme/dsgov/browser/viewlets/configure.zcml
plonetheme/dsgov/browser/viewlets/sections.pt
plonetheme/dsgov/locales/README.rst
plonetheme/dsgov/locales/__init__.py
plonetheme/dsgov/locales/plonetheme.dsgov.pot
plonetheme/dsgov/locales/update.py
plonetheme/dsgov/locales/update.sh
plonetheme/dsgov/locales/en/LC_MESSAGES/plonetheme.dsgov.mo
plonetheme/dsgov/locales/en/LC_MESSAGES/plonetheme.dsgov.po
plonetheme/dsgov/profiles/default/browserlayer.xml
plonetheme/dsgov/profiles/default/catalog.xml
plonetheme/dsgov/profiles/default/controlpanel.xml
plonetheme/dsgov/profiles/default/metadata.xml
plonetheme/dsgov/profiles/default/registry.xml
plonetheme/dsgov/profiles/default/rolemap.xml
plonetheme/dsgov/profiles/default/skins.xml
plonetheme/dsgov/profiles/default/theme.xml
plonetheme/dsgov/profiles/default/registry/main.xml
plonetheme/dsgov/profiles/registerless/metadata.xml
plonetheme/dsgov/profiles/registerless/registry.xml
plonetheme/dsgov/profiles/uninstall/browserlayer.xml
plonetheme/dsgov/tests/__init__.py
plonetheme.dsgov-1.0a6.dist-info/LICENSE.GPL
plonetheme.dsgov-1.0a6.dist-info/LICENSE.rst
plonetheme.dsgov-1.0a6.dist-info/METADATA
plonetheme.dsgov-1.0a6.dist-info/WHEEL
plonetheme.dsgov-1.0a6.dist-info/entry_points.txt
plonetheme.dsgov-1.0a6.dist-info/namespace_packages.txt
plonetheme.dsgov-1.0a6.dist-info/top_level.txt
plonetheme.dsgov-1.0a6.dist-info/RECORD
