Metadata-Version: 2.1
Name: plonetheme.dsgov
Version: 1.0a6
Summary: O Design System do Governo Federal
Home-page: https://github.com/f4biosa/plonetheme.dsgov
Author: Fabio Santos
Author-email: f4bio.sa@gmail.com
License: GPL version 2
Project-URL: PyPI, https://pypi.python.org/pypi/plonetheme.dsgov
Project-URL: Source, https://github.com/f4biosa/plonetheme.dsgov
Project-URL: Tracker, https://github.com/f4biosa/plonetheme.dsgov/issues
Keywords: Python Plone CMS
Platform: UNKNOWN
Classifier: Environment :: Web Environment
Classifier: Framework :: Plone
Classifier: Framework :: Plone :: Addon
Classifier: Framework :: Plone :: 5.2
Classifier: Programming Language :: Python
Classifier: Programming Language :: Python :: 2.7
Classifier: Programming Language :: Python :: 3.7
Classifier: Operating System :: OS Independent
Classifier: License :: OSI Approved :: GNU General Public License v2 (GPLv2)
Requires-Python: ==2.7, >=3.6
License-File: LICENSE.GPL
License-File: LICENSE.rst
Requires-Dist: setuptools
Requires-Dist: plone.app.themingplugins
Requires-Dist: collective.themefragments
Requires-Dist: z3c.jbot
Requires-Dist: plone.api (>=1.8.4)
Requires-Dist: plone.restapi
Requires-Dist: plone.app.dexterity
Requires-Dist: plone.app.mosaic
Requires-Dist: eea.facetednavigation
Requires-Dist: plone.app.registry
Provides-Extra: test
Requires-Dist: plone.app.testing ; extra == 'test'
Requires-Dist: plone.testing (>=5.0.0) ; extra == 'test'
Requires-Dist: plone.app.contenttypes ; extra == 'test'
Requires-Dist: plone.app.robotframework[debug] ; extra == 'test'
